{"is_source_file": true, "format": "JavaScript", "description": "This file defines reusable styling mixins/utilities for a JavaScript project, providing functions for visually hiding content, creating CSS clamp strings, styling cards, and base button styles, and exports them as named functions and a default object.", "external_files": ["./theme.js"], "external_methods": [], "published": ["visuallyHidden", "clampFluid", "card", "buttonBase"], "classes": [], "methods": [{"name": "visuallyHidden()", "description": "Returns an object that visually hides content but keeps it accessible.", "scope": "", "scopeKind": ""}, {"name": "clampFluid(minPx, preferredPx, maxPx)", "description": "Returns a CSS clamp() string for fluid responsive sizing.", "scope": "", "scopeKind": ""}, {"name": "card()", "description": "Creates a style object for a surface card with subtle elevation.", "scope": "", "scopeKind": ""}, {"name": "buttonBase({ variant = 'primary' } = {})", "description": "Provides base visual styles for buttons with accessible contrast and motion.", "scope": "", "scopeKind": ""}], "calls": ["theme.helpers.surfaceLayer", "theme.radius", "theme.tokens.colors.border", "theme.tokens.colors.secondary", "theme.tokens.colors.primary", "theme.tokens.shadows.sm", "theme.transition.fast", "theme.transition.base"], "search-terms": ["mixins", "style utilities", "CSS helpers", "style functions", "button styles", "card styles"], "state": 2, "file_id": 59, "knowledge_revision": 126, "git_revision": "f117debc25f5cfc557e945172cb8340d23b0ddbb", "revision_history": [{"121": "f117debc25f5cfc557e945172cb8340d23b0ddbb"}, {"126": "f117debc25f5cfc557e945172cb8340d23b0ddbb"}], "ctags": [{"_type": "tag", "name": "buttonBase", "path": "/home/kavia/workspace/code-generation/recipe-explorer-176450-176459/recipe_frontend/src/styles/mixins.js", "pattern": "/^export function buttonBase({ variant = 'primary' } = {}) {$/", "language": "JavaScript", "kind": "function", "signature": "({ variant = 'primary' } = {})"}, {"_type": "tag", "name": "card", "path": "/home/kavia/workspace/code-generation/recipe-explorer-176450-176459/recipe_frontend/src/styles/mixins.js", "pattern": "/^export function card() {$/", "language": "JavaScript", "kind": "function", "signature": "()"}, {"_type": "tag", "name": "clampFluid", "path": "/home/kavia/workspace/code-generation/recipe-explorer-176450-176459/recipe_frontend/src/styles/mixins.js", "pattern": "/^export function clampFluid(minPx, preferredPx, maxPx) {$/", "language": "JavaScript", "kind": "function", "signature": "(minPx, preferredPx, maxPx)"}, {"_type": "tag", "name": "visuallyHidden", "path": "/home/kavia/workspace/code-generation/recipe-explorer-176450-176459/recipe_frontend/src/styles/mixins.js", "pattern": "/^export function visuallyHidden() {$/", "language": "JavaScript", "kind": "function", "signature": "()"}], "hash": "33476c0afef2d5633e28edf402c573cd", "format-version": 4, "code-base-name": "recipe_frontend", "filename": "recipe_frontend/src/styles/mixins.js"}